<?xml version="1.0" encoding="utf-8"?>
<b t="Engine Electrical Devices">
<c i="0" t="configtype none title">
<t s="6" t="Repair Instructions">
<s i="S5JB0E1306001" t="Engine Control Module (ECM) Removal and Installation">
</s>
<s i="S5JB0E1306002" t="Manifold Absolute Pressure (MAP) Sensor Inspection">
</s>
<s i="S5JB0E1306003" t="Electric Throttle Body Assembly On-Vehicle Inspection">
</s>
<s i="S5JB0E1306004" t="Electric Throttle Body System Calibration">
</s>
<s i="S5JB0E1306005" t="Accelerator Pedal Position (APP) Sensor Assembly On-Vehicle Inspection">
</s>
<s i="S5JB0E1306006" t="Accelerator Pedal Position (APP) Sensor Assembly Removal and Installation">
</s>
<s i="S5JB0E1306007" t="Accelerator Pedal Position (APP) Sensor Assembly Inspection">
</s>
<s i="S5JB0E1306008" t="Engine Coolant Temperature (ECT) Sensor Removal and Installation">
</s>
<s i="S5JB0E1306009" t="Engine Coolant Temperature (ECT) Sensor Inspection">
</s>
<s i="S5JB0E1306010" t="Air Fuel Ratio (A&#x002F;F) Sensor On-Vehicle Inspection">
</s>
<s i="S5JB0E1306011" t="Heated Oxygen Sensor (HO2S-2) Heater On-Vehicle Inspection">
</s>
<s i="S5JB0E1306012" t="Air Fuel Ratio (A&#x002F;F) Sensor, Heated Oxygen Sensor (HO2S-2) Removal and Installation">
</s>
<s i="S5JB0E1306013" t="Camshaft Position (CMP) Sensor Removal and Installation">
</s>
<s i="S5JB0E1306014" t="Camshaft Position (CMP) Sensor Inspection">
</s>
<s i="S5JB0E1306015" t="Crankshaft Position (CKP) Sensor Removal and Installation">
</s>
<s i="S5JB0E1306016" t="Crankshaft Position (CKP) Sensor Inspection">
</s>
<s i="S5JB0E1306017" t="Knock Sensor Removal and Installation">
</s>
<s i="S5JB0E1306018" t="Control Relay Inspection">
</s>
<s i="S5JB0E1306019" t="Mass Air Flow (MAF) and Intake Air Temperature (IAT) Sensor On-Vehicle Inspection">
</s>
<s i="S5JB0E1306020" t="Mass Air Flow (MAF) and Intake Air Temperature (IAT) Sensor Removal and Installation">
</s>
<s i="S5JB0E1306021" t="Mass Air Flow (MAF) and Intake Air Temperature (IAT) Sensor Inspection">
</s>
<s i="S5JB0E1306022" t="Vacuum Tank Assembly Inspection (For J20 Engine)">
</s>
<s i="S5JB0E1306023" t="Electric Load Current Sensor On-Vehicle Inspection (For J20 Engine)">
</s>
<s i="S5JB0E1306024" t="Electric Load Current Sensor Removal and Installation (For J20 Engine)">
</s>
</t>
<t s="7" t="Specifications">
<s i="S5JB0E1307001" t="Tightening Torque Specifications">
</s>
</t>
</c>
</b>
