<?xml version="1.0" encoding="utf-8"?>
<b t="Engine General Information and Diagnosis">
<c i="0" t="configtype none title">
<t s="0" t="Precautions">
<s i="S6JB0B1100001" t="Precautions on Engine Service">
</s>
<s i="S6JB0B1100002" t="Precautions in Diagnosing Trouble">
</s>
<s i="S6JB0B1100003" t="Precautions for DTC Troubleshooting">
</s>
<s i="S6JB0B1100004" t="Precautions of ECM Circuit Inspection">
</s>
<s i="S6JB0B1100005" t="Precautions of Electric Throttle Body System Calibration">
</s>
</t>
<t s="1" t="General Description">
<s i="S6JB0B1101001" t="Statement of Cleanliness and Care">
</s>
<s i="S6JB0B1101002" t="Engine Diagnosis General Description">
</s>
<s i="S6JB0B1101003" t="On-Board Diagnostic System Description">
</s>
<s i="S6JB0B1101004" t="Engine and Emission Control System Description">
</s>
<s i="S6JB0B1101005" t="Air Intake System Description">
</s>
<s i="S6JB0B1101006" t="Electric Throttle Body System Description">
</s>
<s i="S6JB0B1101007" t="Description of Electric Throttle Body System Calibration">
</s>
<s i="S6JB0B1101008" t="A&#x002F;F Sensor Description">
</s>
<s i="S6JB0B1101009" t="CAN Communication System Description">
</s>
<s i="S6JB0B1101010" t="Electronic Control System Description">
</s>
</t>
<t s="2" t="Schematic and Routing Diagram">
<s i="S6JB0B1102001" t="Engine and Emission Control System Diagram">
</s>
<s i="S6JB0B1102002" t="Electronic Control System Diagram">
</s>
<s i="S6JB0B1102003" t="Electronic Control System Wiring Circuit Diagram">
</s>
</t>
<t s="3" t="Component Location">
<s i="S6JB0B1103001" t="Electronic Control System Location">
</s>
</t>
<t s="4" t="Diagnostic Information and Procedures">
<s i="S6JB0B1104001" t="Engine and Emission Control System Check">
</s>
<s i="S6JB0B1104002" t="Visual Inspection">
</s>
<s i="S6JB0B1104003" t="Engine Basic Check">
</s>
<s i="S6JB0B1104004" t="Malfunction Indicator Lamp (MIL) Check">
</s>
<s i="S6JB0B1104005" t="DTC Table">
</s>
<s i="S6JB0B1104007" t="DTC Check">
</s>
<s i="S6JB0B1104008" t="DTC Clearance">
</s>
<s i="S6JB0B1104009" t="Fail-Safe Table">
</s>
<s i="S6JB0B1104010" t="Scan Tool Data">
</s>
<s i="S6JB0B1104011" t="Engine Symptom Diagnosis">
</s>
<s i="S6JB0B1104012" t="Malfunction Indicator Lamp Does Not Come ON with Ignition Switch ON and Engine Stop (but Engine Can Be Started)">
</s>
<s i="S6JB0B1104013" t="Malfunction Indicator Lamp Remains ON after Engine Starts">
</s>
<s i="S6JB0B1104014" t="DTC P0031 &#x002F; P0032: HO2S Heater Control Circuit Low &#x002F; High (Sensor-1, Bank-1)">
</s>
<s i="S6JB0B1104015" t="DTC P0037 &#x002F; P0038: HO2S Heater Control Circuit Low &#x002F; High (Sensor-2, Bank-1)">
</s>
<s i="S6JB0B1104016" t="DTC P0051 &#x002F; P0052: HO2S Heater Control Circuit Low &#x002F; High (Sensor-1, Bank-2)">
</s>
<s i="S6JB0B1104017" t="DTC P0057 &#x002F; P0058: HO2S Heater Control Circuit Low &#x002F; High (Sensor-2, Bank-2)">
</s>
<s i="S6JB0B1104018" t="DTC P0101: Mass Air Flow Circuit Range &#x002F; Performance">
</s>
<s i="S6JB0B1104019" t="DTC P0102 &#x002F; P0103: Mass Air Flow Circuit Low &#x002F; High Input">
</s>
<s i="S6JB0B1104020" t="DTC P0107 &#x002F; P0108: Manifold Absolute Pressure Sensor Circuit Low &#x002F; High Input">
</s>
<s i="S6JB0B1104021" t="DTC P0111: Intake Air Temperature Sensor Circuit Performance">
</s>
<s i="S6JB0B1104022" t="DTC P0112 &#x002F; P0113: Intake Air Temperature Sensor Circuit Low &#x002F; High Input">
</s>
<s i="S6JB0B1104023" t="DTC P0116: Engine Coolant Temperature Circuit Range &#x002F; Performance">
</s>
<s i="S6JB0B1104024" t="DTC P0117 &#x002F; P0118: Engine Coolant Temperature Circuit Low &#x002F; High Input">
</s>
<s i="S6JB0B1104025" t="DTC P0122 &#x002F; P0123: Throttle Position Sensor (Main) Circuit Low &#x002F; High Input">
</s>
<s i="S6JB0B1104026" t="DTC P0133 &#x002F; P2A00: O2 Sensor Circuit Slow Response &#x002F; Performance (Sensor-1, Bank-1)">
</s>
<s i="S6JB0B1104027" t="DTC P0134: O2 Sensor Circuit No Activity (Sensor-1, Bank-1)">
</s>
<s i="S6JB0B1104028" t="DTC P0137 &#x002F; P0138: O2 Sensor Circuit Low Voltage &#x002F; High Voltage (Sensor-2, Bank-1)">
</s>
<s i="S6JB0B1104029" t="DTC P0140: O2 Sensor Circuit No Activity Detected (Sensor-2, Bank-1)">
</s>
<s i="S6JB0B1104030" t="DTC P0153 &#x002F; P2A03: O2 Sensor Circuit Slow Response &#x002F; Performance (Sensor-1, Bank-2)">
</s>
<s i="S6JB0B1104031" t="DTC P0154: O2 Sensor Circuit No Activity (Sensor-1, Bank-2)">
</s>
<s i="S6JB0B1104032" t="DTC P0157 &#x002F; P0158: O2 Sensor Circuit Low Voltage &#x002F; High Voltage (Sensor-2, Bank-2)">
</s>
<s i="S6JB0B1104033" t="DTC P0160: O2 Sensor Circuit No Activity Detected (Sensor-2, Bank-2)">
</s>
<s i="S6JB0B1104034" t="DTC P0171 &#x002F; P0172: System Too Lean &#x002F; Too Rich (Sensor-1, Bank-1)">
</s>
<s i="S6JB0B1104035" t="DTC P0174 &#x002F; P0175: System Too Lean &#x002F; Too Rich (Sensor-1, Bank-2)">
</s>
<s i="S6JB0B1104036" t="DTC P0222 &#x002F; P0223: Throttle Position Sensor (Sub) Circuit Low&#x002F;High">
</s>
<s i="S6JB0B1104037" t="DTC P0300 &#x002F; P0301 &#x002F; P0302 &#x002F; P0303 &#x002F; P0304 &#x002F; P0305 &#x002F; P0306: Misfire Detected">
</s>
<s i="S6JB0B1104038" t="DTC P0327 &#x002F; P0328: Knock Sensor Circuit Low &#x002F; High">
</s>
<s i="S6JB0B1104039" t="DTC P0335: Crankshaft Position Sensor Circuit">
</s>
<s i="S6JB0B1104040" t="DTC P0336: Crankshaft Position Sensor Circuit Range &#x002F; Performance">
</s>
<s i="S6JB0B1104041" t="DTC P0340: Camshaft Position Sensor Circuit">
</s>
<s i="S6JB0B1104042" t="DTC P0341: Camshaft Position Sensor Circuit Range &#x002F; Performance">
</s>
<s i="S6JB0B1104043" t="DTC P0401 &#x002F; P0402: Exhaust Gas Recirculation Flow Insufficient Detected &#x002F; Excessive Detected">
</s>
<s i="S6JB0B1104044" t="DTC P0403: Exhaust Gas Recirculation Control Circuit">
</s>
<s i="S6JB0B1104045" t="DTC P0420 &#x002F; P0430: Catalyst System Efficiency Below Threshold (Bank-1 &#x002F; -2)">
</s>
<s i="S6JB0B1104046" t="DTC P0444 &#x002F; P0445: EVAP Emission System Purge Control Valve Circuit Open &#x002F; Shorted">
</s>
<s i="S6JB0B1104047" t="DTC P0462 &#x002F; P0463: Fuel Level Sensor Circuit Low &#x002F; High">
</s>
<s i="S6JB0B1104048" t="DTC P0480 &#x002F; P0481 &#x002F; P0482: Fan 1 &#x002F; Fan 2 &#x002F; Fan 3 Control Circuit">
</s>
<s i="S6JB0B1104049" t="DTC P0500: Vehicle Speed Sensor">
</s>
<s i="S6JB0B1104050" t="DTC P0532 &#x002F; P0533: A&#x002F;C Refrigerant Pressure Sensor Circuit Low &#x002F; High">
</s>
<s i="S6JB0B1104051" t="DTC P0601 &#x002F; P0602 &#x002F; P0607: Internal Control Module Memory Check Sum Error &#x002F; Control Module Programming Error &#x002F; Control Module Performance">
</s>
<s i="S6JB0B1104052" t="DTC P0616 &#x002F; P0617: Starter Relay Circuit Low &#x002F; High">
</s>
<s i="S6JB0B1104053" t="DTC P0645: A&#x002F;C Clutch Relay Control Circuit">
</s>
<s i="S6JB0B1104054" t="DTC P0661 &#x002F; P0662: Intake Manifold Tuning Valve Control Circuit Low &#x002F; High">
</s>
<s i="S6JB0B1104055" t="DTC P1107 &#x002F; P1108: Manifold Absolute Pressure Sensor Rationality Check - Low &#x002F; High">
</s>
<s i="S6JB0B1104056" t="DTC P1510: ECM Back-Up Power Supply Malfunction">
</s>
<s i="S6JB0B1104057" t="DTC P1603: TCM Trouble Code Detected">
</s>
<s i="S6JB0B1104058" t="DTC P2101: Throttle Actuator Control Motor Circuit Range &#x002F; Performance">
</s>
<s i="S6JB0B1104059" t="DTC P2102: Throttle Actuator Control Motor Circuit Low">
</s>
<s i="S6JB0B1104060" t="DTC P2103: Throttle Actuator Control Motor Circuit High">
</s>
<s i="S6JB0B1104061" t="DTC P2108: Throttle Actuator Control Module Performance">
</s>
<s i="S6JB0B1104062" t="DTC P2119: Throttle Actuator Control Throttle Body Range &#x002F; Performance">
</s>
<s i="S6JB0B1104063" t="DTC P2122 &#x002F; P2123: Pedal Position Sensor (Main) Circuit Low &#x002F; High">
</s>
<s i="S6JB0B1104064" t="DTC P2127 &#x002F; P2128: Pedal Position Sensor (Sub) Circuit Low &#x002F; High">
</s>
<s i="S6JB0B1104065" t="DTC P2135: Throttle Position Sensor (Main &#x002F; Sub) Voltage Correction">
</s>
<s i="S6JB0B1104066" t="DTC P2138: Pedal Position Sensor (Main &#x002F; Sub) Voltage Correction">
</s>
<s i="S6JB0B1104067" t="DTC P2195 &#x002F; P2196: O2 Sensor Signal Stuck Lean &#x002F; Stuck Rich (Sensor-1, Bank-1)">
</s>
<s i="S6JB0B1104068" t="DTC P2197 &#x002F; P2198: O2 Sensor Signal Stuck Lean &#x002F; Stuck Rich (Sensor-1, Bank-2)">
</s>
<s i="S6JB0B1104069" t="DTC P2227&#x002F; P2228 &#x002F; P2229: Barometric Pressure Circuit Malfunction">
</s>
<s i="S6JB0B1104070" t="DTC P2237: O2 Sensor Positive Current Control Circuit &#x002F; Open (Sensor-1, Bank-1)">
</s>
<s i="S6JB0B1104071" t="DTC P2238 &#x002F; P2239: O2 Sensor Positive Current Control Circuit Low &#x002F; High (Sensor-1, Bank-1)">
</s>
<s i="S6JB0B1104072" t="DTC P2240: O2 Sensor Positive Current Control Circuit &#x002F; Open (Sensor-1, Bank-2)">
</s>
<s i="S6JB0B1104073" t="DTC P2241 &#x002F; P2242: O2 Sensor Positive Current Control Circuit Low &#x002F; High (Sensor-1, Bank-2)">
</s>
<s i="S6JB0B1104074" t="DTC P2252 &#x002F; P2253: O2 Sensor Negative Current Control Circuit Low&#x002F;High (Sensor-1, Bank-1)">
</s>
<s i="S6JB0B1104075" t="DTC P2255 &#x002F; P2256: O2 Sensor Negative Current Control Circuit Low&#x002F;High (Sensor-1, Bank-2)">
</s>
<s i="S6JB0B1104076" t="DTC P2627 &#x002F; P2628: O2 Sensor Pumping Current Trim Circuit Low &#x002F; High (Sensor-1, Bank-1)">
</s>
<s i="S6JB0B1104077" t="DTC P2630 &#x002F; P2631: O2 Sensor Pumping Current Trim Circuit Low &#x002F; High (Sensor-1, Bank-2)">
</s>
<s i="S6JB0B1104078" t="DTC P2A01: O2 Sensor Circuit Performance (Sensor-2, Bank-1)">
</s>
<s i="S6JB0B1104079" t="DTC P2A04: O2 Sensor Circuit Performance (Sensor-2, Bank-2)">
</s>
<s i="S6JB0B1104080" t="DTC U0073: Control Module Communication Bus Off">
</s>
<s i="S6JB0B1104081" t="DTC U0101: Lost Communication with TCM">
</s>
<s i="S6JB0B1104082" t="DTC U0121: Lost Communication with Electronic Stability Program &#x002F; ABS Control Module">
</s>
<s i="S6JB0B1104083" t="DTC U0140: Lost Communication with Body Control Module">
</s>
<s i="S6JB0B1104084" t="Inspection of ECM and Its Circuits">
</s>
<s i="S6JB0B1104085" t="ECM Power and Ground Circuit Check">
</s>
<s i="S6JB0B1104086" t="Fuel Injector Circuit Check">
</s>
<s i="S6JB0B1104087" t="Fuel Pump and Its Circuit Check">
</s>
<s i="S6JB0B1104088" t="Fuel Pressure Check">
</s>
<s i="S6JB0B1104089" t="A&#x002F;C System Circuits Check">
</s>
<s i="S6JB0B1104090" t="Electric Load Signal Circuit Check">
</s>
<s i="S6JB0B1104091" t="Radiator Cooling Fan Low Speed Control System Check">
</s>
<s i="S6JB0B1104092" t="Radiator Cooling Fan High Speed Control System Check">
</s>
</t>
<t s="6" t="Repair Instructions">
<s i="S6JB0B1106001" t="Idle Speed and IAC Throttle Valve Opening Inspection">
</s>
</t>
<t s="8" t="Special Tools and Equipment">
<s i="S6JB0B1108001" t="Special Tool">
</s>
</t>
</c>
</b>
