<?xml version="1.0" encoding="utf-8"?>
<b t="Vorsichtsmaßnahmen" >
<c i="0" t="configtype none title" >
<t s="0" t="Vorsichtsmaßnahmen" >
<s i="G8T40A0000001" t="Vorsichtsmaßnahmen für Fahrzeuge mit Zusatzrückhaltesystem (Airbag)">
</s>
<s i="G8T40A0000002" t="Allgemeine Vorsichtsmaßnahmen">
</s>
<s i="G8T40A0000003" t="Vorsichtsmaßnahme bei der Wartung von Fahrzeugen mit permanentem Allradantrieb">
</s>
<s i="G8T40A0000004" t="Vorsichtsmaßnahmen bei Fahrzeugen mit ESP&#174;-System">
</s>
<s i="G8T40A0000005" t="Vorsichtsmaßnahmen beim Katalysator (Benzinmotor-Modell)">
</s>
<s i="G8T40A0000006" t="Vorsichtsmaßnahmen bei Katalysator und Dieselpartikelfilter (Dieselmotor-Modell)">
</s>
<s i="G8T40A0000007" t="Vorsichtsmaßnahme für das CAN-Datenbussystem">
</s>
<s i="G8T40A0000008" t="Vorsichtsmaßnahmen bei Wartungsarbeiten an elektrischen Schaltkreisen">
</s>
<s i="G8T40A0000009" t="Vorsichtsmaßnahmen für den Einbau von Autotelefon und Mobilfunk">
</s>
<s i="G8T40A0000010" t="Airbag-Warnhinweis">
</s>
<s i="G8T40A0000011" t="Warnhinweis für die Lichtbogen-Entladelampe">
</s>
<s i="G8T40A0000012" t="Vorsichtsmaßnahmen bezüglich der Klimaanlage">
</s>
<s i="G8T40A0000013" t="Vorsichtsmaßnahmen bei den Befestigungsteilen">
</s>
<s i="G8T40A0000014" t="Vorsichtsmaßnahmen bei der Radaufhängung">
</s>
<s i="G8T40A0000015" t="Vorsichtsmaßnahmen bezüglich der Räder und Reifen">
</s>
<s i="G8T40A0000016" t="Vorsichtsmaßnahmen und Hinweis zu den Bremsen">
</s>
<s i="G8T40A0000017" t="Hinweise zum Differentialgetriebeöl">
</s>
</t>
<t s="6" t="Reparaturanweisungen" >
<s i="G8T40A0006001" t="Vorgehensweise für die Überprüfung der elektrischen Schaltkreise">
</s>
<s i="G8T40A0006002" t="Überprüfung auf Wackelkontakte und schlechte Verbindungen">
</s>
</t>
</c>
</b>
