<?xml version="1.0" encoding="utf-8"?>
<b t="Automatische Geschwindigkeitsregelung" >
<c i="0" t="configtype none title" >
<t s="1" t="Allgemeines" >
<s i="G5JB0EA101001" t="Bauweise automatische Geschwindigkeitsregelung">
</s>
<s i="G5JB0EA101005" t="Bauteile der Geschwindigkeitsregelung und deren Funktion">
</s>
<s i="G5JB0EA101003" t="Ausschaltbedingungen der Geschwindigkeitsregelung">
</s>
</t>
<t s="2" t="Schaltbild und Kabelführungsdiagramm" >
<s i="G5JB0EA102002" t="Eingabe-&#x002F;Ausgabe-Diagramm des Tempomatsystems">
</s>
<s i="G5JB0EA102001" t="Schaltplan Geschwindigkeitsregelung">
</s>
</t>
<t s="4" t="Information zur Diagnose und Arbeitsverfahren" >
<s i="G5JB0EA104001" t="Symptomdiagnose der Geschwindigkeitsregelung">
</s>
<s i="G5JB0EA104002" t="Überprüfung des Schaltkreises der Geschwindigkeitsregelung">
</s>
</t>
<t s="6" t="Reparaturanweisungen" >
<s i="G5JB0EA106001" t="Aus- und Einbau des Schalters der Geschwindigkeitsregelung">
</s>
<s i="G5JB0EA106002" t="Überprüfung des Schalters der Geschwindigkeitsregelung">
</s>
<s i="G5JB0EA106003" t="Aus- und Einbau des CPP-Schalters (für Geschwindigkeitsregelung)">
</s>
<s i="G5JB0EA106004" t="Überprüfung und Einstellung des Kupplungspedal-Positionsschalters (CPP) (für Geschwindigkeitsregelung)">
</s>
<s i="G5JB0EA106005" t="Aus- und Einbau des Bremslichtschalters">
</s>
<s i="G5JB0EA106006" t="Prüfung des Bremslichtschalters">
</s>
<s i="G5JB0EA106007" t="Aus- und Einbau des ECM">
</s>
</t>
<t s="7" t="Technische Daten" >
<s i="G5JB0EA107001" t="Vorgeschriebene Anzugsmomente">
</s>
</t>
</c>
</b>
