<?xml version="1.0" encoding="utf-8"?>
<b t="Ladesystem" >
<c i="0" t="configtype none title" >
<t s="1" t="Allgemeines" >
<s i="G5JB0E1A01001" t="Beschreibung der Batterie">
</s>
<s i="G5JB0E1A01002" t="Beschreibung der Lichtmaschine">
</s>
</t>
<t s="4" t="Information zur Diagnose und Arbeitsverfahren" >
<s i="G5JB0E1A04001" t="Überprüfung der Batterie">
</s>
<s i="G5JB0E1A04002" t="Symptomdiagnose der Lichtmaschine">
</s>
<s i="G5JB0E1A04003" t="Lichtmaschinentest (Überprüfung bei schwacher Batterie)">
</s>
<s i="G5JB0E1A04004" t="Lichtmaschinentest (Überprüfung bei überladener Batterie)">
</s>
</t>
<t s="6" t="Reparaturanweisungen" >
<s i="G5JB0E1A06001" t="Anlassen mit Starthilfekabel im Notfall">
</s>
<s i="G5JB0E1A06002" t="Aus- und Einbau der Batterie">
</s>
<s i="G5JB0E1A06003" t="Aus- und Einbau des Antriebsriemens der Wasserpumpe und der Lichtmaschine (Für M16-Motor)">
</s>
<s i="G5JB0E1A06004" t="Überprüfung und Einstellung des Antriebsriemens der Wasserpumpe und der Lichtmaschine (Für M16-Motor)">
</s>
<s i="G5JB0E1A06005" t="Überprüfung des Antriebsriemens der Wasserpumpe und der Lichtmaschine am Fahrzeug (Für J20-Motor)">
</s>
<s i="G5JB0E1A06006" t="Aus- und Einbau des Antriebsriemens der Wasserpumpe und der Lichtmaschine (Für J20-Motor)">
</s>
<s i="G5JB0E1A06007" t="Aus- und Einbau der Lichtmaschine">
</s>
<s i="G5JB0E1A06008" t="Bauteile der Lichtmaschine">
</s>
<s i="G5JB0E1A06009" t="Überprüfung der Lichtmaschine">
</s>
</t>
<t s="7" t="Technische Daten" >
<s i="G5JB0E1A07001" t="Technische Daten des Ladesystems">
</s>
<s i="G5JB0E1A07002" t="Vorgeschriebene Anzugsmomente">
</s>
</t>
</c>
</b>
