<?xml version="1.0" encoding="utf-8"?>
<b t="Protection et serrures" >
<c i="0" t="configtype none title" >
<t s="1" t="Description générale" >
<s i="F5JB0A9601001" t="Construction du codage de clé">
</s>
</t>
<t s="3" t="Emplacement des composants" >
<s i="F5JB0A9603001" t="Emplacement des composants de la serrure électrique de portière et du système de télécommande">
</s>
</t>
<t s="4" t="Informations de diagnostic et procédures" >
<s i="F5JB0A9604001" t="Diagnostic des symptômes du système de verrouillage central des portes">
</s>
<s i="F5JB0A9604002" t="Vérification du fonctionnement du système de verrouillage central des portes">
</s>
<s i="F5JB0A9604004" t="Diagnostic des symptômes du système de verrouillage des portes par télécommande (si le véhicule en est équipé)">
</s>
<s i="F5JB0A9604005" t="Vérification du fonctionnement du système de la télécommande">
</s>
<s i="F5JB0A9604010" t="Diagnostic des symptômes de la fonction de verrouillage des portières du système de démarrage par télécommande (si le véhicule en est équipé)">
</s>
</t>
<t s="6" t="Instructions pour la réparation" >
<s i="F5JB0A9606001" t="Composants de l&apos;ensemble de serrure de porte avant">
</s>
<s i="F5JB0A9606002" t="Dépose et repose de l&apos;ensemble de serrure de porte avant">
</s>
<s i="F5JB0A9606003" t="Vérification de l&apos;ensemble de serrure de porte avant">
</s>
<s i="F5JB0A9606004" t="Vérification du contacteur de verrouillage central des portes">
</s>
<s i="F5JB0A9606005" t="Vérification du contacteur de barillet de serrure de porte">
</s>
<s i="F5JB0A9606006" t="Vérification de l&apos;actionneur de verrouillage central des portes (si le véhicule en est équipé)">
</s>
<s i="F5JB0A9606007" t="Composants de l&apos;ensemble de serrure de portière arrière">
</s>
<s i="F5JB0A9606008" t="Dépose et repose de l&apos;ensemble de serrure de porte arrière">
</s>
<s i="F5JB0A9606009" t="Vérification de l&apos;ensembe de serrure de porte arrière">
</s>
<s i="F5JB0A9606010" t="Composants de l&apos;ensemble de serrure de porte de coffre arrière">
</s>
<s i="F5JB0A9606011" t="Dépose et repose de l&apos;ensemble de serrure de porte du coffre arrière">
</s>
<s i="F5JB0A9606012" t="Vérification de l&apos;ensemble de serrure de porte du coffre arrière">
</s>
<s i="F5JB0A9606014" t="Remplacement de la pile de la télécommande">
</s>
<s i="F5JB0A9606015" t="Programmation du code de la télécommande pour le système de verrouillage des portes par télécommande (véhicule équipé du système de verrouillage des portes par télécommande)">
</s>
<s i="F5JB0A9606016" t="Dépose et repose du récepteur de la télécommande">
</s>
<s i="F5JB0A9606017" t="Vérification du récepteur de la télécommande et de son circuit">
</s>
</t>
<t s="7" t="Spécifications" >
<s i="F5JB0A9607001" t="Spécifications de couple de serrage">
</s>
</t>
<t s="8" t="Outils spéciaux et matériel" >
<s i="F5JB0A9608001" t="Produits d&apos;entretien recommandés">
</s>
</t>
</c>
</b>
